phoenixAES/__init__.py
phoenixAES-0.0.5.dist-info/LICENSE
phoenixAES-0.0.5.dist-info/METADATA
phoenixAES-0.0.5.dist-info/WHEEL
phoenixAES-0.0.5.dist-info/top_level.txt
phoenixAES-0.0.5.dist-info/RECORD
