Metadata-Version: 2.1
Name: phoenixAES
Version: 0.0.5
Summary: tool to perform differential fault analysis attacks (DFA) against AES
Home-page: https://github.com/SideChannelMarvels/JeanGrey
Author: Philippe Teuwen
Author-email: phil@teuwen.org
Classifier: Programming Language :: Python :: 3
Classifier: License :: OSI Approved :: GNU General Public License v3 or later (GPLv3+)
Classifier: Operating System :: OS Independent
Classifier: Development Status :: 4 - Beta
Classifier: Intended Audience :: Science/Research
Classifier: Topic :: Security :: Cryptography
License-File: LICENSE
